Project.srcs/Vending_Machine.v
`timescale 1ns / 1ps

// Engineer: Mohd. Wasim Akhtar
// 
// Create Date: 14.09.2025 12:49:40
// Design Name: 
// Module Name: Vending_Machine



module Vending_Machine(coin, clk, reset, Z, change_given);
    input wire clk, reset;
    input wire [1:0] coin ;
    output reg Z, change_given ;
    
     // States 
     parameter Sin=4'b0000, S10 = 4'b0001, S20 = 4'b0010, S30 = 4'b0011,
     S40 = 4'b0100, S50 = 4'b0101, S60 = 4'b0110, S70 = 4'b0111, S80 = 4'b1000;
     // coin inserted 
     parameter ten = 2'b00, twenty = 2'b01, fifty = 2'b10;
    reg [3:0] state, next_state;
    always @(posedge clk, posedge reset) begin
    if(reset == 1)
    state <= Sin;
    else
    state <= next_state; end
     always @(state, coin)begin
      case (state)
        Sin:begin
        if(coin == ten)
         next_state = S10;
        else if (coin == twenty)
         next_state = S20;
        else
         next_state = S50;
        end 

        S10:begin
        if(coin == ten)
         next_state = S20;
        else if (coin == twenty)
         next_state = S30;
        else
         next_state = S60;
        end
        
        S20: begin
        if(coin == ten)
         next_state = S30;
        else if (coin == twenty)
         next_state = S40;
        else if (coin == fifty)
         next_state = S70;
         end 
         
        S30: begin
        if(coin == ten)
         next_state = S40;
        else if (coin == twenty)
         next_state = S50;
        else
         next_state = S80;
        end 
        S40:next_state = Sin;
        S50:next_state = Sin;
        S60:next_state = Sin;
        S70:next_state = Sin;
        S80:next_state = Sin;
        default: next_state = Sin;
       endcase
      end
     // Now alloting the output values
     always @(state, coin) begin
      case (state)
        Sin: begin Z = 0; change_given = 0; end
        S10: begin Z = 0; change_given = 0; end
        S20: begin Z = 0; change_given = 0; end
        S30: begin Z = 0; change_given = 0; end
        S40: begin Z = 1; change_given = 0; end
        S50: begin Z = 1; change_given = 1; end
        S60: begin Z = 1; change_given = 1; end
        S70: begin Z = 1; change_given = 1; end
        S80: begin Z = 1; change_given = 1; end
      endcase 
      end
endmodule

Project.srcs/Vending_Machine_tb.v
`timescale 1ns / 1ps

module Vending_Machine_tb;
    // Inputs
    reg clk;
    reg reset;
    reg [1:0] coin;
    
    // Outputs
    wire Z;
    wire change_given;
    
    // Instantiate the Unit Under Test (UUT)
    Vending_Machine uut (
        .coin(coin),
        .clk(clk),
        .reset(reset),
        .Z(Z),
        .change_given(change_given)
    );
    
    // Define clock period
    parameter CLK_PERIOD = 10;
    
    // Generate clock
    always #(CLK_PERIOD/2) clk = ~clk;
    
    // Define coin values for readability
    parameter ten = 2'b00, twenty = 2'b01, fifty = 2'b10;
    
    // Test sequence
    initial begin
        // Initialize Inputs
        clk = 0;
        reset = 1;
        coin = 0;
        
        // Apply reset
        #(CLK_PERIOD*2) reset = 0;
        
        // Test case 1: Insert 10+10+10+10 coins (40 cents)
        #(CLK_PERIOD) coin = ten;
        #(CLK_PERIOD) coin = ten;
        #(CLK_PERIOD) coin = ten;
        #(CLK_PERIOD) coin = ten;
        #(CLK_PERIOD) coin = 0; // No coin
        
        // Test case 2: Insert 20+20 coins (40 cents)
        #(CLK_PERIOD*2) coin = twenty;
        #(CLK_PERIOD) coin = twenty;
        #(CLK_PERIOD) coin = 0;
        
        // Test case 3: Insert 50 coin (50 cents - should get change)
        #(CLK_PERIOD*2) coin = fifty;
        #(CLK_PERIOD) coin = 0;
        
        // Test case 4: Insert 10+20+10 coins (40 cents)
        #(CLK_PERIOD*2) coin = ten;
        #(CLK_PERIOD) coin = twenty;
        #(CLK_PERIOD) coin = ten;
        #(CLK_PERIOD) coin = 0;
        
        // Test case 5: Insert 50+10 coins (60 cents - should get change)
        #(CLK_PERIOD*2) coin = fifty;
        #(CLK_PERIOD) coin = ten;
        #(CLK_PERIOD) coin = 0;
        
        // End simulation
        #(CLK_PERIOD*5) $finish;
    end
    
    // Monitor to display outputs
    initial begin
        $monitor("Time=%0t, Reset=%b, Coin=%b, State=%b, Z=%b, Change=%b", 
                 $time, reset, coin, uut.state, Z, change_given);
    end
    
    // Generate waveform file for debugging
    initial begin
        $dumpfile("vending_machine.vcd");
        $dumpvars(0, Vending_Machine_tb);
    end
endmodule

Projects.sim/vending_machine.vcd
$date
   Sun Sep 14 13:23:27 2025
$end

$version
  2025.1.0
  $dumpfile ("vending_machine.vcd") 
$end

$timescale
  1ps
$end

$scope module Vending_Machine_tb $end
$var reg 1 ! clk $end
$var reg 1 " reset $end
$var reg 2 # coin [1:0] $end
$var wire 1 $ Z $end
$var wire 1 % change_given $end
$scope module uut $end
$var wire 1 & clk $end
$var wire 1 ' reset $end
$var wire 2 ( coin [1:0] $end
$var reg 1 ) Z $end
$var reg 1 * change_given $end
$var reg 4 + state [3:0] $end
$var reg 4 , next_state [3:0] $end
$upscope $end
$upscope $end
$enddefinitions $end

#0
$dumpvars
0!
1"
b0 #
0$
0%
0&
1'
b0 (
0)
0*
b0 +
b1 ,
$end

#5000
1!
1&

#10000
0!
0&

#15000
1!
1&

#20000
0!
0"
0&
0'

#25000
1!
1&
b1 +
b10 ,

#30000
0!
0&

#35000
1!
1&
b10 +
b11 ,

#40000
0!
0&

#45000
1!
1&
b11 +
b100 ,

#50000
0!
0&

#55000
1!
1$
1&
1)
b100 +
b0 ,

#60000
0!
0&

#65000
1!
0$
1&
0)
b0 +
b1 ,

#70000
0!
0&

#75000
1!
1&
b1 +
b10 ,

#80000
0!
0&

#85000
1!
1&
b10 +
b11 ,

#90000
0!
b1 #
0&
b1 (
b100 ,

#95000
1!
1$
1&
1)
b100 +
b0 ,

#100000
0!
0&

#105000
1!
0$
1&
0)
b0 +
b10 ,

#110000
0!
b0 #
0&
b0 (
b1 ,

#115000
1!
1&
b1 +
b10 ,

#120000
0!
0&

#125000
1!
1&
b10 +
b11 ,

#130000
0!
b10 #
0&
b10 (
b111 ,

#135000
1!
1$
1%
1&
1)
1*
b111 +
b0 ,

#140000
0!
b0 #
0&
b0 (

#145000
1!
0$
0%
1&
0)
0*
b0 +
b1 ,

#150000
0!
0&

#155000
1!
1&
b1 +
b10 ,

#160000
0!
0&

#165000
1!
1&
b10 +
b11 ,

#170000
0!
b1 #
0&
b1 (
b100 ,

#175000
1!
1$
1&
1)
b100 +
b0 ,

#180000
0!
b0 #
0&
b0 (

#185000
1!
0$
1&
0)
b0 +
b1 ,

#190000
0!
0&

#195000
1!
1&
b1 +
b10 ,

#200000
0!
0&

#205000
1!
1&
b10 +
b11 ,

#210000
0!
b10 #
0&
b10 (
b111 ,

#215000
1!
1$
1%
1&
1)
1*
b111 +
b0 ,

#220000
0!
b0 #
0&
b0 (

#225000
1!
0$
0%
1&
0)
0*
b0 +
b1 ,

#230000
0!
0&

#235000
1!
1&
b1 +
b10 ,

#240000
0!
0&

#245000
1!
1&
b10 +
b11 ,

#250000
0!
0&

#255000
1!
1&
b11 +
b100 ,

#260000
0!
0&

#265000
1!
1$
1&
1)
b100 +
b0 ,

#270000
0!
0&

#275000
1!
0$
1&
0)
b0 +
b1 ,
